LICENSE
README.md
setup.py
DeepDict/__init__.py
DeepDict/main.py
PathLikeDict.egg-info/PKG-INFO
PathLikeDict.egg-info/SOURCES.txt
PathLikeDict.egg-info/dependency_links.txt
PathLikeDict.egg-info/top_level.txt