Metadata-Version: 2.1
Name: PathLikeDict
Version: 0.0.1
Summary: 借鉴 pathlib.Path 链式操作方式，简化深字典的操作。
Home-page: https://gitee.com/colorthoro/py-path-like-dict
Author: colorthoro
Author-email: dream.0112@qq.com
License: MIT
Requires-Python: >=3.10
License-File: LICENSE
